[{"player_id": 10, "action": "serve", "frame": 10, "action_conf": 0.05770757049322128}, {"player_id": 10, "action": "serve", "frame": 11, "action_conf": 0.324800580739975}, {"player_id": 10, "action": "serve", "frame": 12, "action_conf": 0.08074697107076645}, {"player_id": 10, "action": "serve", "frame": 13, "action_conf": 0.07548133283853531}, {"player_id": 10, "action": "serve", "frame": 14, "action_conf": 0.04171396791934967}, {"player_id": 13, "action": "block", "frame": 14, "action_conf": 0.021274888888001442}, {"player_id": 10, "action": "serve", "frame": 15, "action_conf": 0.04882444441318512}, {"player_id": 10, "action": "serve", "frame": 20, "action_conf": 0.020119568333029747}, {"player_id": 10, "action": "serve", "frame": 27, "action_conf": 0.02373233623802662}, {"player_id": 10, "action": "serve", "frame": 28, "action_conf": 0.025605211034417152}, {"player_id": 10, "action": "serve", "frame": 33, "action_conf": 0.026158472523093224}, {"player_id": 10, "action": "serve", "frame": 34, "action_conf": 0.026848092675209045}, {"player_id": 10, "action": "serve", "frame": 35, "action_conf": 0.05352168530225754}, {"player_id": 10, "action": "serve", "frame": 36, "action_conf": 0.05126306787133217}, {"player_id": 10, "action": "serve", "frame": 38, "action_conf": 0.02686150372028351}, {"player_id": 13, "action": "serve", "frame": 61, "action_conf": 0.07795637100934982}, {"player_id": 13, "action": "serve", "frame": 62, "action_conf": 0.14769834280014038}, {"player_id": 13, "action": "serve", "frame": 63, "action_conf": 0.1328737735748291}, {"player_id": 13, "action": "serve", "frame": 64, "action_conf": 0.08227936178445816}, {"player_id": 13, "action": "serve", "frame": 65, "action_conf": 0.08630441129207611}, {"player_id": 13, "action": "serve", "frame": 66, "action_conf": 0.13987384736537933}, {"player_id": 13, "action": "serve", "frame": 67, "action_conf": 0.14226360619068146}, {"player_id": 13, "action": "serve", "frame": 70, "action_conf": 0.028057163581252098}, {"player_id": 13, "action": "serve", "frame": 71, "action_conf": 0.02902023307979107}, {"player_id": 13, "action": "serve", "frame": 72, "action_conf": 0.07402391731739044}, {"player_id": 9, "action": "set", "frame": 157, "action_conf": 0.3088358938694}, {"player_id": 9, "action": "set", "frame": 158, "action_conf": 0.570168673992157}, {"player_id": 9, "action": "set", "frame": 159, "action_conf": 0.6455108523368835}, {"player_id": 9, "action": "set", "frame": 160, "action_conf": 0.3933337926864624}, {"player_id": 9, "action": "set", "frame": 161, "action_conf": 0.7926271557807922}, {"player_id": 9, "action": "set", "frame": 162, "action_conf": 0.8108543753623962}, {"player_id": 9, "action": "set", "frame": 163, "action_conf": 0.7997554540634155}, {"player_id": 9, "action": "set", "frame": 164, "action_conf": 0.7996698021888733}, {"player_id": 9, "action": "set", "frame": 165, "action_conf": 0.8432639241218567}, {"player_id": 9, "action": "set", "frame": 166, "action_conf": 0.8138201236724854}, {"player_id": 9, "action": "set", "frame": 167, "action_conf": 0.8445137143135071}, {"player_id": 9, "action": "set", "frame": 168, "action_conf": 0.8492439389228821}, {"player_id": 9, "action": "set", "frame": 169, "action_conf": 0.8681260943412781}, {"player_id": 9, "action": "set", "frame": 170, "action_conf": 0.8437741994857788}, {"player_id": 9, "action": "set", "frame": 171, "action_conf": 0.8595584630966187}, {"player_id": 9, "action": "set", "frame": 172, "action_conf": 0.8502316474914551}, {"player_id": 9, "action": "set", "frame": 173, "action_conf": 0.753079891204834}, {"player_id": 9, "action": "set", "frame": 174, "action_conf": 0.831622838973999}, {"player_id": 9, "action": "set", "frame": 175, "action_conf": 0.8543322682380676}, {"player_id": 9, "action": "set", "frame": 176, "action_conf": 0.8720301985740662}, {"player_id": 9, "action": "set", "frame": 177, "action_conf": 0.8715952038764954}, {"player_id": 9, "action": "set", "frame": 178, "action_conf": 0.8574232459068298}, {"player_id": 9, "action": "set", "frame": 179, "action_conf": 0.8719744682312012}, {"player_id": 9, "action": "set", "frame": 180, "action_conf": 0.8750680685043335}, {"player_id": 9, "action": "set", "frame": 181, "action_conf": 0.8252145648002625}, {"player_id": 9, "action": "set", "frame": 182, "action_conf": 0.7503200173377991}, {"player_id": 38, "action": "set", "frame": 183, "action_conf": 0.5363341569900513}, {"player_id": 9, "action": "set", "frame": 184, "action_conf": 0.2650323212146759}, {"player_id": 9, "action": "spike", "frame": 201, "action_conf": 0.03093455545604229}, {"player_id": 9, "action": "spike", "frame": 202, "action_conf": 0.06396372616291046}, {"player_id": 9, "action": "spike", "frame": 203, "action_conf": 0.13940992951393127}, {"player_id": 9, "action": "spike", "frame": 204, "action_conf": 0.14975005388259888}, {"player_id": 15, "action": "block", "frame": 204, "action_conf": 0.042600732296705246}, {"player_id": 9, "action": "spike", "frame": 205, "action_conf": 0.31628066301345825}, {"player_id": 9, "action": "spike", "frame": 206, "action_conf": 0.03067304939031601}, {"player_id": 18, "action": "set", "frame": 209, "action_conf": 0.0330912284553051}, {"player_id": 18, "action": "set", "frame": 218, "action_conf": 0.022133998572826385}, {"player_id": 18, "action": "set", "frame": 219, "action_conf": 0.020019272342324257}, {"player_id": 18, "action": "spike", "frame": 220, "action_conf": 0.199472114443779}, {"player_id": 12, "action": "block", "frame": 220, "action_conf": 0.13006971776485443}, {"player_id": 38, "action": "block", "frame": 220, "action_conf": 0.29573309421539307}, {"player_id": 18, "action": "spike", "frame": 221, "action_conf": 0.2039037048816681}, {"player_id": 12, "action": "block", "frame": 221, "action_conf": 0.12681029736995697}, {"player_id": 38, "action": "block", "frame": 221, "action_conf": 0.30257469415664673}, {"player_id": 18, "action": "spike", "frame": 222, "action_conf": 0.14666159451007843}, {"player_id": 38, "action": "block", "frame": 222, "action_conf": 0.32688575983047485}, {"player_id": 38, "action": "block", "frame": 223, "action_conf": 0.07690862566232681}, {"player_id": 18, "action": "spike", "frame": 224, "action_conf": 0.053723935037851334}, {"player_id": 38, "action": "block", "frame": 224, "action_conf": 0.8305752873420715}, {"player_id": 8, "action": "spike", "frame": 225, "action_conf": 0.035824671387672424}, {"player_id": 38, "action": "block", "frame": 225, "action_conf": 0.7087609171867371}, {"player_id": 8, "action": "spike", "frame": 226, "action_conf": 0.07194437086582184}, {"player_id": 38, "action": "block", "frame": 226, "action_conf": 0.7905020117759705}, {"player_id": 8, "action": "spike", "frame": 227, "action_conf": 0.07844383269548416}, {"player_id": 38, "action": "block", "frame": 227, "action_conf": 0.788050651550293}, {"player_id": 8, "action": "spike", "frame": 228, "action_conf": 0.04850016161799431}, {"player_id": 38, "action": "block", "frame": 228, "action_conf": 0.7600398063659668}, {"player_id": 38, "action": "block", "frame": 229, "action_conf": 0.22231093049049377}, {"player_id": 8, "action": "spike", "frame": 230, "action_conf": 0.03185701742768288}, {"player_id": 38, "action": "block", "frame": 230, "action_conf": 0.1349117010831833}, {"player_id": 1, "action": "defense", "frame": 235, "action_conf": 0.022763529792428017}, {"player_id": 1, "action": "defense", "frame": 236, "action_conf": 0.024263976141810417}, {"player_id": 2, "action": "set", "frame": 237, "action_conf": 0.0961032509803772}, {"player_id": 2, "action": "set", "frame": 239, "action_conf": 0.10993582010269165}, {"player_id": 2, "action": "set", "frame": 240, "action_conf": 0.35436028242111206}, {"player_id": 8, "action": "spike", "frame": 243, "action_conf": 0.02314985916018486}, {"player_id": 8, "action": "spike", "frame": 244, "action_conf": 0.021365217864513397}, {"player_id": 8, "action": "spike", "frame": 245, "action_conf": 0.13396736979484558}, {"player_id": 49, "action": "set", "frame": 247, "action_conf": 0.028938036412000656}, {"player_id": 49, "action": "set", "frame": 248, "action_conf": 0.028826134279370308}, {"player_id": 49, "action": "set", "frame": 249, "action_conf": 0.031589314341545105}, {"player_id": 3, "action": "set", "frame": 266, "action_conf": 0.026769546791911125}, {"player_id": 3, "action": "set", "frame": 269, "action_conf": 0.16556544601917267}, {"player_id": 3, "action": "set", "frame": 270, "action_conf": 0.20082683861255646}, {"player_id": 3, "action": "set", "frame": 271, "action_conf": 0.5505363345146179}, {"player_id": 3, "action": "set", "frame": 272, "action_conf": 0.6174118518829346}, {"player_id": 3, "action": "set", "frame": 273, "action_conf": 0.5571773648262024}, {"player_id": 3, "action": "set", "frame": 274, "action_conf": 0.0415068082511425}, {"player_id": 3, "action": "set", "frame": 275, "action_conf": 0.0209982767701149}, {"player_id": 3, "action": "set", "frame": 276, "action_conf": 0.021553795784711838}, {"player_id": 3, "action": "set", "frame": 277, "action_conf": 0.08786340057849884}, {"player_id": 3, "action": "set", "frame": 278, "action_conf": 0.2763308882713318}, {"player_id": 10, "action": "set", "frame": 278, "action_conf": 0.1488686352968216}, {"player_id": 3, "action": "set", "frame": 279, "action_conf": 0.0938509851694107}, {"player_id": 10, "action": "set", "frame": 279, "action_conf": 0.025978898629546165}, {"player_id": 3, "action": "set", "frame": 280, "action_conf": 0.09168543666601181}, {"player_id": 10, "action": "set", "frame": 280, "action_conf": 0.020312895998358727}, {"player_id": 3, "action": "set", "frame": 281, "action_conf": 0.02159007079899311}, {"player_id": 3, "action": "set", "frame": 283, "action_conf": 0.10657176375389099}, {"player_id": 3, "action": "set", "frame": 284, "action_conf": 0.10405994206666946}, {"player_id": 25, "action": "serve", "frame": 328, "action_conf": 0.03358829766511917}, {"player_id": 9, "action": "set", "frame": 339, "action_conf": 0.05151248723268509}, {"player_id": 9, "action": "set", "frame": 340, "action_conf": 0.07983022928237915}, {"player_id": 9, "action": "set", "frame": 341, "action_conf": 0.18593154847621918}, {"player_id": 9, "action": "set", "frame": 349, "action_conf": 0.03474229946732521}, {"player_id": 37, "action": "defense", "frame": 349, "action_conf": 0.02094978652894497}, {"player_id": 9, "action": "defense", "frame": 351, "action_conf": 0.0211174376308918}, {"player_id": 9, "action": "defense", "frame": 352, "action_conf": 0.04441880062222481}, {"player_id": 37, "action": "set", "frame": 352, "action_conf": 0.028437035158276558}, {"player_id": 9, "action": "defense", "frame": 357, "action_conf": 0.023147620260715485}, {"player_id": 25, "action": "serve", "frame": 358, "action_conf": 0.02206142619252205}, {"player_id": 25, "action": "serve", "frame": 359, "action_conf": 0.03409331291913986}, {"player_id": 9, "action": "set", "frame": 361, "action_conf": 0.3778497576713562}, {"player_id": 9, "action": "set", "frame": 362, "action_conf": 0.4514423608779907}, {"player_id": 9, "action": "set", "frame": 363, "action_conf": 0.472582072019577}, {"player_id": 15, "action": "defense", "frame": 363, "action_conf": 0.02517915889620781}, {"player_id": 9, "action": "set", "frame": 364, "action_conf": 0.22150203585624695}, {"player_id": 9, "action": "set", "frame": 365, "action_conf": 0.1316622793674469}, {"player_id": 25, "action": "serve", "frame": 365, "action_conf": 0.050090495496988297}, {"player_id": 15, "action": "defense", "frame": 365, "action_conf": 0.02060941606760025}, {"player_id": 9, "action": "set", "frame": 366, "action_conf": 0.5591526627540588}, {"player_id": 9, "action": "set", "frame": 367, "action_conf": 0.059381354600191116}, {"player_id": 42, "action": "set", "frame": 367, "action_conf": 0.4412880539894104}, {"player_id": 9, "action": "set", "frame": 368, "action_conf": 0.538549542427063}, {"player_id": 9, "action": "set", "frame": 369, "action_conf": 0.3017810583114624}, {"player_id": 9, "action": "set", "frame": 370, "action_conf": 0.6811771392822266}, {"player_id": 9, "action": "set", "frame": 371, "action_conf": 0.7130658626556396}, {"player_id": 9, "action": "set", "frame": 372, "action_conf": 0.7720745205879211}, {"player_id": 9, "action": "set", "frame": 373, "action_conf": 0.6773802638053894}, {"player_id": 9, "action": "set", "frame": 374, "action_conf": 0.7462191581726074}, {"player_id": 9, "action": "set", "frame": 375, "action_conf": 0.5104387402534485}, {"player_id": 24, "action": "defense", "frame": 375, "action_conf": 0.02844308875501156}, {"player_id": 9, "action": "set", "frame": 376, "action_conf": 0.43188562989234924}, {"player_id": 25, "action": "spike", "frame": 376, "action_conf": 0.0533035546541214}, {"player_id": 9, "action": "set", "frame": 377, "action_conf": 0.12321842461824417}, {"player_id": 9, "action": "set", "frame": 380, "action_conf": 0.0892404317855835}, {"player_id": 24, "action": "defense", "frame": 380, "action_conf": 0.022815857082605362}, {"player_id": 12, "action": "spike", "frame": 380, "action_conf": 0.020160486921668053}, {"player_id": 9, "action": "spike", "frame": 381, "action_conf": 0.10523606836795807}, {"player_id": 24, "action": "set", "frame": 381, "action_conf": 0.05158703774213791}, {"player_id": 12, "action": "defense", "frame": 381, "action_conf": 0.026970598846673965}, {"player_id": 9, "action": "set", "frame": 389, "action_conf": 0.020346082746982574}, {"player_id": 24, "action": "serve", "frame": 420, "action_conf": 0.024847717955708504}, {"player_id": 25, "action": "serve", "frame": 438, "action_conf": 0.5253337621688843}, {"player_id": 24, "action": "serve", "frame": 439, "action_conf": 0.3076835572719574}, {"player_id": 24, "action": "serve", "frame": 440, "action_conf": 0.3008648455142975}, {"player_id": 24, "action": "serve", "frame": 441, "action_conf": 0.28815919160842896}, {"player_id": 25, "action": "serve", "frame": 442, "action_conf": 0.21838900446891785}, {"player_id": 24, "action": "serve", "frame": 444, "action_conf": 0.02427055686712265}, {"player_id": 24, "action": "serve", "frame": 445, "action_conf": 0.025261256843805313}, {"player_id": 42, "action": "set", "frame": 446, "action_conf": 0.5836783051490784}, {"player_id": 42, "action": "set", "frame": 447, "action_conf": 0.8167253136634827}, {"player_id": 42, "action": "set", "frame": 448, "action_conf": 0.8811285495758057}, {"player_id": 42, "action": "set", "frame": 449, "action_conf": 0.8781576752662659}, {"player_id": 42, "action": "set", "frame": 450, "action_conf": 0.8678408861160278}, {"player_id": 42, "action": "set", "frame": 451, "action_conf": 0.8760325908660889}, {"player_id": 42, "action": "set", "frame": 452, "action_conf": 0.8807355761528015}, {"player_id": 42, "action": "set", "frame": 453, "action_conf": 0.8732253909111023}, {"player_id": 42, "action": "set", "frame": 454, "action_conf": 0.8612259030342102}, {"player_id": 42, "action": "set", "frame": 455, "action_conf": 0.8612820506095886}, {"player_id": 42, "action": "set", "frame": 456, "action_conf": 0.8850192427635193}, {"player_id": 42, "action": "set", "frame": 457, "action_conf": 0.8798553943634033}, {"player_id": 42, "action": "set", "frame": 458, "action_conf": 0.8503427505493164}, {"player_id": 42, "action": "set", "frame": 459, "action_conf": 0.8498721718788147}, {"player_id": 42, "action": "set", "frame": 460, "action_conf": 0.8679749369621277}, {"player_id": 42, "action": "set", "frame": 461, "action_conf": 0.8329825401306152}, {"player_id": 42, "action": "set", "frame": 462, "action_conf": 0.8416063785552979}, {"player_id": 42, "action": "set", "frame": 463, "action_conf": 0.841464638710022}, {"player_id": 42, "action": "set", "frame": 464, "action_conf": 0.6729950308799744}, {"player_id": 42, "action": "set", "frame": 465, "action_conf": 0.7832337617874146}, {"player_id": 42, "action": "set", "frame": 466, "action_conf": 0.3055277466773987}, {"player_id": 42, "action": "set", "frame": 467, "action_conf": 0.3059157729148865}, {"player_id": 42, "action": "set", "frame": 468, "action_conf": 0.0873420238494873}, {"player_id": 12, "action": "set", "frame": 468, "action_conf": 0.09801240265369415}, {"player_id": 42, "action": "set", "frame": 469, "action_conf": 0.09149428457021713}, {"player_id": 25, "action": "spike", "frame": 480, "action_conf": 0.03656710684299469}, {"player_id": 42, "action": "block", "frame": 480, "action_conf": 0.023334858939051628}, {"player_id": 25, "action": "spike", "frame": 482, "action_conf": 0.023564394563436508}, {"player_id": 25, "action": "spike", "frame": 483, "action_conf": 0.024028949439525604}, {"player_id": 42, "action": "spike", "frame": 484, "action_conf": 0.03107721358537674}, {"player_id": 107, "action": "set", "frame": 488, "action_conf": 0.03687357157468796}, {"player_id": 1, "action": "set", "frame": 506, "action_conf": 0.30099132657051086}, {"player_id": 1, "action": "set", "frame": 507, "action_conf": 0.2807702124118805}, {"player_id": 1, "action": "set", "frame": 508, "action_conf": 0.767376720905304}, {"player_id": 3, "action": "set", "frame": 508, "action_conf": 0.18360677361488342}, {"player_id": 1, "action": "set", "frame": 509, "action_conf": 0.058014921844005585}, {"player_id": 9, "action": "set", "frame": 509, "action_conf": 0.2246038317680359}, {"player_id": 3, "action": "set", "frame": 509, "action_conf": 0.04705719277262688}, {"player_id": 3, "action": "set", "frame": 513, "action_conf": 0.6014565229415894}, {"player_id": 3, "action": "set", "frame": 514, "action_conf": 0.22502943873405457}, {"player_id": 3, "action": "set", "frame": 515, "action_conf": 0.18920759856700897}, {"player_id": 3, "action": "set", "frame": 516, "action_conf": 0.3523749113082886}, {"player_id": 3, "action": "set", "frame": 517, "action_conf": 0.29585567116737366}, {"player_id": 3, "action": "set", "frame": 518, "action_conf": 0.16864526271820068}, {"player_id": 3, "action": "set", "frame": 519, "action_conf": 0.26137787103652954}, {"player_id": 3, "action": "set", "frame": 520, "action_conf": 0.4628226161003113}, {"player_id": 3, "action": "set", "frame": 521, "action_conf": 0.35101208090782166}, {"player_id": 3, "action": "set", "frame": 522, "action_conf": 0.45228925347328186}, {"player_id": 3, "action": "set", "frame": 523, "action_conf": 0.3216983377933502}, {"player_id": 3, "action": "set", "frame": 524, "action_conf": 0.22828221321105957}, {"player_id": 3, "action": "spike", "frame": 525, "action_conf": 0.3349353075027466}, {"player_id": 3, "action": "spike", "frame": 526, "action_conf": 0.4412402808666229}, {"player_id": 3, "action": "spike", "frame": 527, "action_conf": 0.3847757577896118}, {"player_id": 3, "action": "block", "frame": 528, "action_conf": 0.29912158846855164}, {"player_id": 3, "action": "block", "frame": 529, "action_conf": 0.21436214447021484}, {"player_id": 10, "action": "spike", "frame": 529, "action_conf": 0.17204180359840393}, {"player_id": 3, "action": "spike", "frame": 530, "action_conf": 0.13099567592144012}, {"player_id": 10, "action": "block", "frame": 530, "action_conf": 0.05519145354628563}, {"player_id": 3, "action": "spike", "frame": 531, "action_conf": 0.21150611340999603}, {"player_id": 10, "action": "set", "frame": 531, "action_conf": 0.04747583344578743}, {"player_id": 3, "action": "spike", "frame": 532, "action_conf": 0.30553531646728516}, {"player_id": 10, "action": "block", "frame": 532, "action_conf": 0.03260032832622528}, {"player_id": 3, "action": "spike", "frame": 533, "action_conf": 0.35315659642219543}, {"player_id": 10, "action": "set", "frame": 533, "action_conf": 0.03390853852033615}, {"player_id": 3, "action": "spike", "frame": 534, "action_conf": 0.04342197626829147}, {"player_id": 3, "action": "spike", "frame": 535, "action_conf": 0.34040531516075134}, {"player_id": 9, "action": "block", "frame": 535, "action_conf": 0.043337203562259674}, {"player_id": 3, "action": "spike", "frame": 536, "action_conf": 0.22926859557628632}, {"player_id": 9, "action": "block", "frame": 536, "action_conf": 0.028669660910964012}, {"player_id": 10, "action": "block", "frame": 536, "action_conf": 0.07021180540323257}, {"player_id": 37, "action": "set", "frame": 536, "action_conf": 0.027788683772087097}, {"player_id": 3, "action": "set", "frame": 537, "action_conf": 0.059687450528144836}, {"player_id": 9, "action": "block", "frame": 537, "action_conf": 0.100015789270401}, {"player_id": 10, "action": "spike", "frame": 537, "action_conf": 0.051022980362176895}, {"player_id": 3, "action": "spike", "frame": 538, "action_conf": 0.0420604944229126}, {"player_id": 10, "action": "set", "frame": 538, "action_conf": 0.040461279451847076}, {"player_id": 3, "action": "set", "frame": 539, "action_conf": 0.05141865089535713}, {"player_id": 10, "action": "spike", "frame": 539, "action_conf": 0.036257725208997726}, {"player_id": 1, "action": "defense", "frame": 620, "action_conf": 0.03988540172576904}, {"player_id": 1, "action": "defense", "frame": 621, "action_conf": 0.03939644247293472}, {"player_id": 7, "action": "spike", "frame": 640, "action_conf": 0.036535605788230896}]