[{"player_id": 59, "action": "set", "frame": 393, "action_conf": 0.43644267320632935}, {"player_id": 59, "action": "set", "frame": 394, "action_conf": 0.3581791818141937}, {"player_id": 59, "action": "set", "frame": 395, "action_conf": 0.3263540267944336}, {"player_id": 59, "action": "set", "frame": 396, "action_conf": 0.03195277974009514}, {"player_id": 59, "action": "set", "frame": 397, "action_conf": 0.048611342906951904}, {"player_id": 59, "action": "set", "frame": 398, "action_conf": 0.04824100807309151}, {"player_id": 59, "action": "set", "frame": 399, "action_conf": 0.3739413321018219}, {"player_id": 61, "action": "block", "frame": 437, "action_conf": 0.23294420540332794}, {"player_id": 61, "action": "block", "frame": 441, "action_conf": 0.06848308444023132}, {"player_id": 61, "action": "block", "frame": 442, "action_conf": 0.0719539150595665}, {"player_id": 61, "action": "block", "frame": 443, "action_conf": 0.6802796721458435}, {"player_id": 59, "action": "block", "frame": 443, "action_conf": 0.803836464881897}, {"player_id": 61, "action": "block", "frame": 444, "action_conf": 0.7923877239227295}, {"player_id": 59, "action": "block", "frame": 444, "action_conf": 0.8014708161354065}, {"player_id": 61, "action": "block", "frame": 445, "action_conf": 0.7216479778289795}, {"player_id": 74, "action": "block", "frame": 445, "action_conf": 0.6963133215904236}, {"player_id": 81, "action": "block", "frame": 445, "action_conf": 0.0244759488850832}, {"player_id": 73, "action": "block", "frame": 445, "action_conf": 0.02836468070745468}, {"player_id": 61, "action": "block", "frame": 446, "action_conf": 0.6808815002441406}, {"player_id": 81, "action": "block", "frame": 446, "action_conf": 0.7941269278526306}, {"player_id": 61, "action": "block", "frame": 447, "action_conf": 0.05341620370745659}, {"player_id": 74, "action": "block", "frame": 447, "action_conf": 0.823944091796875}, {"player_id": 54, "action": "block", "frame": 447, "action_conf": 0.6898757815361023}, {"player_id": 61, "action": "block", "frame": 448, "action_conf": 0.7138475179672241}, {"player_id": 74, "action": "block", "frame": 448, "action_conf": 0.8333573341369629}, {"player_id": 61, "action": "block", "frame": 449, "action_conf": 0.5952621698379517}, {"player_id": 74, "action": "block", "frame": 449, "action_conf": 0.81348717212677}, {"player_id": 61, "action": "block", "frame": 450, "action_conf": 0.4591718018054962}, {"player_id": 74, "action": "block", "frame": 450, "action_conf": 0.8565354347229004}, {"player_id": 54, "action": "block", "frame": 450, "action_conf": 0.3955940008163452}, {"player_id": 61, "action": "block", "frame": 451, "action_conf": 0.33383315801620483}, {"player_id": 74, "action": "block", "frame": 451, "action_conf": 0.8732060790061951}, {"player_id": 54, "action": "block", "frame": 451, "action_conf": 0.05264192074537277}, {"player_id": 61, "action": "block", "frame": 452, "action_conf": 0.36979103088378906}, {"player_id": 74, "action": "block", "frame": 452, "action_conf": 0.8430392146110535}, {"player_id": 61, "action": "block", "frame": 453, "action_conf": 0.1328597217798233}, {"player_id": 74, "action": "block", "frame": 453, "action_conf": 0.8314180374145508}, {"player_id": 54, "action": "block", "frame": 453, "action_conf": 0.02817114256322384}, {"player_id": 12, "action": "block", "frame": 453, "action_conf": 0.15707799792289734}, {"player_id": 61, "action": "block", "frame": 454, "action_conf": 0.0656735897064209}, {"player_id": 74, "action": "block", "frame": 454, "action_conf": 0.844758927822113}, {"player_id": 54, "action": "block", "frame": 454, "action_conf": 0.020052677020430565}, {"player_id": 61, "action": "block", "frame": 455, "action_conf": 0.09040772169828415}, {"player_id": 74, "action": "block", "frame": 455, "action_conf": 0.8728921413421631}, {"player_id": 61, "action": "block", "frame": 456, "action_conf": 0.1235630139708519}, {"player_id": 74, "action": "block", "frame": 456, "action_conf": 0.8448246717453003}, {"player_id": 61, "action": "block", "frame": 457, "action_conf": 0.057175926864147186}, {"player_id": 74, "action": "block", "frame": 457, "action_conf": 0.8453191518783569}, {"player_id": 61, "action": "block", "frame": 458, "action_conf": 0.03445570543408394}, {"player_id": 74, "action": "block", "frame": 458, "action_conf": 0.8126917481422424}, {"player_id": 61, "action": "block", "frame": 459, "action_conf": 0.8042923212051392}, {"player_id": 61, "action": "block", "frame": 460, "action_conf": 0.8038683533668518}, {"player_id": 61, "action": "block", "frame": 461, "action_conf": 0.7815521359443665}, {"player_id": 61, "action": "block", "frame": 462, "action_conf": 0.7096805572509766}, {"player_id": 61, "action": "block", "frame": 463, "action_conf": 0.5019656419754028}, {"player_id": 61, "action": "block", "frame": 464, "action_conf": 0.06857644021511078}, {"player_id": 61, "action": "block", "frame": 465, "action_conf": 0.3877955973148346}, {"player_id": 61, "action": "block", "frame": 466, "action_conf": 0.3111887574195862}, {"player_id": 61, "action": "block", "frame": 467, "action_conf": 0.03828471899032593}, {"player_id": 59, "action": "block", "frame": 467, "action_conf": 0.22412849962711334}, {"player_id": 61, "action": "block", "frame": 468, "action_conf": 0.6535604000091553}, {"player_id": 61, "action": "block", "frame": 469, "action_conf": 0.5310512185096741}, {"player_id": 61, "action": "block", "frame": 470, "action_conf": 0.12308861315250397}, {"player_id": 59, "action": "block", "frame": 470, "action_conf": 0.5188689827919006}, {"player_id": 61, "action": "block", "frame": 471, "action_conf": 0.5235728025436401}, {"player_id": 61, "action": "block", "frame": 472, "action_conf": 0.03106304258108139}, {"player_id": 59, "action": "block", "frame": 472, "action_conf": 0.07550935447216034}, {"player_id": 61, "action": "block", "frame": 473, "action_conf": 0.10350966453552246}, {"player_id": 61, "action": "block", "frame": 474, "action_conf": 0.07326585799455643}, {"player_id": 61, "action": "block", "frame": 475, "action_conf": 0.12031476199626923}]